{
    "nets": [
        {
            "name": "net0",
            "gwip": "10.2.1.1/24",
            "vlan": "17"
        },
        {
            "name": "net1",
            "gwip": "10.2.2.1/24",
            "vlan": "18"
        },
        {
            "name": "net2-dhcp",
            "gwip": "10.2.0.1/24",
            "vlan": "19"
        },        
        {
            "name": "net3",
            "gwip": "10.10.0.1/24",
            "vlan": "30"
        },
        {
            "name": "net4",
            "gwip": "10.10.4.1/24",
            "vlan": "31"
        },
        {
            "name": "net5",
            "gwip": "10.10.8.1/24",
            "vlan": "32"
        },
        {
            "name": "net6-dhcp",
            "gwip": "172.17.254.1/24",
            "vlan": "33"
        },
        {
            "name": "net7-dhcp",
            "gwip": "172.18.254.1/24",
            "vlan": "18"
        },
        {
            "name": "net8",
            "gwip": "10.99.0.1/24",
            "vlan": "99"
        }
    ]
}